Workbook

Sheet Valuation
A2: Assumptions
A3: Interest Income in 2013 | B3: USD Million | C3: 17593
A4: Interest Expense | C4: 0.4135 | F4: Return on Equity | H4: =C11+(C10*C12) -> 0.104305
A5: Non Interest Income | C5: 0.4804 | F5: Market Capitalization | G5: USD Million | H5: =C9*C16 -> 35676.9
A6: Provision for Credit Losses | C6: 0.0858 | F6: Book Value of Equity | G6: USD Million | H6: =C9*C14 -> 46234.35
A7: Non Interest Expense | C7: 0.5847 | F7: Total Debt | G7: USD Million | H7: 143800
A8: Income Taxes | C8: 0.2871 | F8: Total Cash | G8: USD Million | H8: 146800
A9: Ordinary Shares Outstanding | B9: Million | C9: 2427
A10: Equity Beta | C10: 1.23
A11: UK Government Bond Yield | C11: 0.0262
A12: Market Risk Premium | C12: 0.0635
A13: Dividend Per Share in 2014 | B13: USD | C13: 0.86
A14: Book Value Per Share | B14: USD | C14: 19.05
A15: Share Price | B15: GBP | C15: =14.7*0.65 -> 9.555
A16: Share Price | B16: USD | C16: 14.7
A19: Valuation
A20: Discounted FCFE Method | B20: 37.72
A21: DDM | B21: =DDM!C10 -> 21.871676
A22: Comprables (P/E) | B22: =Comparables!K4 -> 19.85694
A23: Comprables (P/S) | B23: =Comparables!K5 -> 16.976698
A24: Comprables (P/B) | B24: =Comparables!K6 -> 14.097
A25: Average Comparables | B25: =AVERAGE(B22:B24) -> 16.976879

Sheet FCFE
B1: INCOME STATEMENT FOR STANDARD CHARTERED BANK (US$ Million)
C2: Year 0 | D2: Year 1 | E2: Year 2 | F2: Year 3 | G2: Year 4 | H2: Year 5 | I2: Year 6 | J2: Year 7 | K2: Year 8 | L2: Year 9 | M2: Year 10
C3: 2014 | D3: 2015 | E3: 2016 | F3: 2017 | G3: 2018 | H3: 2019 | I3: 2020 | J3: 2021 | K3: 2022 | L3: 2023 | M3: 2024
B4: Interest Income Growth | C4: 0.0248 | D4: 0.0248 | E4: 0.0248 | F4: 0.045 | G4: 0.045 | H4: 0.045 | I4: 0.045 | J4: 0.045 | K4: 0.045 | L4: 0.045 | M4: 0.05
B5: Interest Income | C5: =Valuation!$C$3*(1+FCFE!C4) -> 18029.306 | D5: =C5*(1+D4) -> 18476.433 | E5: =D5*(1+E4) -> 18934.649 | F5: =E5*(1+F4) -> 19786.708 | G5: =F5*(1+G4) -> 20677.11 | H5: =G5*(1+H4) -> 21607.58 | I5: =H5*(1+I4) -> 22579.921 | J5: =I5*(1+J4) -> 23596.017 | K5: =J5*(1+K4) -> 24657.838 | ... M5: =L5*(1+M4) -> 27055.813
B6: Interest Expense | C6: =C5*Valuation!$C$4 -> 7455.1182 | D6: =D5*Valuation!$C$4 -> 7640.0051 | E6: =E5*Valuation!$C$4 -> 7829.4773 | F6: =F5*Valuation!$C$4 -> 8181.8037 | G6: =G5*Valuation!$C$4 -> 8549.9849 | H6: =H5*Valuation!$C$4 -> 8934.7342 | I6: =I5*Valuation!$C$4 -> 9336.7973 | J6: =J5*Valuation!$C$4 -> 9756.9531 | ... M6: =M5*Valuation!$C$4 -> 11187.579
B7: Net interest Income | C7: =C5-C6 -> 10574.188 | D7: =D5-D6 -> 10836.428 | E7: =E5-E6 -> 11105.171 | F7: =F5-F6 -> 11604.904 | G7: =G5-G6 -> 12127.125 | H7: =H5-H6 -> 12672.846 | I7: =I5-I6 -> 13243.124 | J7: =J5-J6 -> 13839.064 | ... M7: =M5-M6 -> 15868.234
B8: Non - Interest Income | C8: =C5*Valuation!$C$5 -> 8661.2788 | D8: =D5*Valuation!$C$5 -> 8876.0785 | E8: =E5*Valuation!$C$5 -> 9096.2053 | F8: =F5*Valuation!$C$5 -> 9505.5345 | G8: =G5*Valuation!$C$5 -> 9933.2835 | H8: =H5*Valuation!$C$5 -> 10380.281 | I8: =I5*Valuation!$C$5 -> 10847.394 | J8: =J5*Valuation!$C$5 -> 11335.527 | ... M8: =M5*Valuation!$C$5 -> 12997.612
B9: Total income | C9: =C7+C8 -> 19235.467 | D9: =D7+D8 -> 19712.507 | E9: =E7+E8 -> 20201.377 | F9: =F7+F8 -> 21110.439 | G9: =G7+G8 -> 22060.408 | H9: =H7+H8 -> 23053.127 | I9: =I7+I8 -> 24090.518 | J9: =J7+J8 -> 25174.591 | ... M9: =M7+M8 -> 28865.847
B10: Provision for credit losses | C10: =C5*Valuation!$C$6 -> 1546.9145 | D10: =D5*Valuation!$C$6 -> 1585.278 | E10: =E5*Valuation!$C$6 -> 1624.5929 | F10: =F5*Valuation!$C$6 -> 1697.6995 | G10: =G5*Valuation!$C$6 -> 1774.096 | H10: =H5*Valuation!$C$6 -> 1853.9303 | I10: =I5*Valuation!$C$6 -> 1937.3572 | J10: =J5*Valuation!$C$6 -> 2024.5383 | ... M10: =M5*Valuation!$C$6 -> 2321.3887
B11: Gross Income | C11: =C9-C10 -> 17688.553 | D11: =D9-D10 -> 18127.229 | E11: =E9-E10 -> 18576.784 | F11: =F9-F10 -> 19412.739 | G11: =G9-G10 -> 20286.312 | H11: =H9-H10 -> 21199.196 | I11: =I9-I10 -> 22153.16 | J11: =J9-J10 -> 23150.053 | ... M11: =M9-M10 -> 26544.458
B12: Non-interest Expense | C12: =C5*Valuation!$C$7 -> 10541.735 | D12: =D5*Valuation!$C$7 -> 10803.17 | E12: =E5*Valuation!$C$7 -> 11071.089 | F12: =F5*Valuation!$C$7 -> 11569.288 | G12: =G5*Valuation!$C$7 -> 12089.906 | H12: =H5*Valuation!$C$7 -> 12633.952 | I12: =I5*Valuation!$C$7 -> 13202.48 | J12: =J5*Valuation!$C$7 -> 13796.591 | ... M12: =M5*Valuation!$C$7 -> 15819.534
B13: Profit Before Tax | C13: =C11-C12 -> 7146.8171 | D13: =D11-D12 -> 7324.0581 | E13: =E11-E12 -> 7505.6948 | F13: =F11-F12 -> 7843.451 | G13: =G11-G12 -> 8196.4063 | H13: =H11-H12 -> 8565.2446 | I13: =I11-I12 -> 8950.6806 | J13: =J11-J12 -> 9353.4612 | ... M13: =M11-M12 -> 10724.924
B14: Income Tax | C14: =C13*Valuation!$C$8 -> 2051.8512 | D14: =D13*Valuation!$C$8 -> 2102.7371 | E14: =E13*Valuation!$C$8 -> 2154.885 | F14: =F13*Valuation!$C$8 -> 2251.8548 | G14: =G13*Valuation!$C$8 -> 2353.1883 | H14: =H13*Valuation!$C$8 -> 2459.0817 | I14: =I13*Valuation!$C$8 -> 2569.7404 | J14: =J13*Valuation!$C$8 -> 2685.3787 | ... M14: =M13*Valuation!$C$8 -> 3079.1257
B15: Net Income | C15: =C13-C14 -> 5094.9659 | D15: =D13-D14 -> 5221.321 | E15: =E13-E14 -> 5350.8098 | F15: =F13-F14 -> 5591.5962 | G15: =G13-G14 -> 5843.2181 | H15: =H13-H14 -> 6106.1629 | I15: =I13-I14 -> 6380.9402 | J15: =J13-J14 -> 6668.0825 | ... M15: =M13-M14 -> 7645.7985
B16: EPS | C16: =C15/Valuation!$C$9 -> 2.0992855 | D16: =D15/Valuation!$C$9 -> 2.1513478 | E16: =E15/Valuation!$C$9 -> 2.2047012 | F16: =F15/Valuation!$C$9 -> 2.3039127 | G16: =G15/Valuation!$C$9 -> 2.4075888 | H16: =H15/Valuation!$C$9 -> 2.5159303 | I16: =I15/Valuation!$C$9 -> 2.6291472 | J16: =J15/Valuation!$C$9 -> 2.7474588 | ... M16: =M15/Valuation!$C$9 -> 3.1503084
B18: Assumptions
B19: The valuation assumes that capital spending & net operating working capital are negligible
B20: No adjustments for outstanding warrants & share options are made in calculating value per share
B21: Terminal Growth rate | C21: 0.05
B24: DISCOUNTED CASH FLOW TO EQUITY VALUATION (US$ Million)
C25: Year 0 | D25: Year 1 | E25: Year 2 | F25: Year 3 | G25: Year 4 | H25: Year 5 | I25: Year 6 | J25: Year 7 | K25: Year 8 | L25: Year 9 | M25: Year 10
C26: 2014 | D26: 2015 | E26: 2016 | F26: 2017 | G26: 2018 | H26: 2019 | I26: 2020 | J26: 2021 | K26: 2022 | L26: 2023 | M26: 2024
B27: Net Income | C27: =C15 -> 5094.9659 | D27: =D15 -> 5221.321 | E27: =E15 -> 5350.8098 | F27: =F15 -> 5591.5962 | G27: =G15 -> 5843.2181 | H27: =H15 -> 6106.1629 | I27: =I15 -> 6380.9402 | J27: =J15 -> 6668.0825 | ... M27: =M15 -> 7645.7985
B28: Depreciation | C28: 0 | D28: 0 | E28: 0 | F28: 0 | G28: 0 | H28: 0 | I28: 0 | J28: 0 | K28: 0 | L28: 0
B29: Capital Expenditure | C29: 0 | D29: 0 | E29: 0 | F29: 0 | G29: 0 | H29: 0 | I29: 0 | J29: 0 | K29: 0 | L29: 0
B30: Increase in WC | C30: 0 | D30: 0 | E30: 0 | F30: 0 | G30: 0 | H30: 0 | I30: 0 | J30: 0 | K30: 0 | L30: 0
B31: Net Borrowings | C31: 0 | D31: 0 | E31: 0 | F31: 0 | G31: 0 | H31: 0 | I31: 0 | J31: 0 | K31: 0 | L31: 0
B32: FCFE | C32: =C27 -> 5094.9659 | D32: =D27 -> 5221.321 | E32: =E27 -> 5350.8098 | F32: =F27 -> 5591.5962 | G32: =G27 -> 5843.2181 | H32: =H27 -> 6106.1629 | I32: =I27 -> 6380.9402 | J32: =J27 -> 6668.0825 | ... M32: =M27 -> 7645.7985
B33: Terminal Value of the Firm | L33: =L32*(1+C21)/(Valuation!H4-FCFE!C21) -> 140793.64
B34: FCFE + Terminal value | C34: =C32+C33 -> 5094.9659 | D34: =D32+D33 -> 5221.321 | E34: =E32+E33 -> 5350.8098 | F34: =F32+F33 -> 5591.5962 | G34: =G32+G33 -> 5843.2181 | H34: =H32+H33 -> 6106.1629 | I34: =I32+I33 -> 6380.9402 | J34: =J32+J33 -> 6668.0825 | ... M34: =M32+M33 -> 7645.7985
B36: Discounted FCFE at the end of 2014 | C36: =NPV(Valuation!$H$4,FCFE!D34:M34) -> 94377.873
B37: Value per Share | C37: =C36/Valuation!C9 -> 38.886639

Sheet DDM
B2: DISCOUNTED FREE CASH FLOW VALUATION
C3: Year 0 | D3: Year 1 | E3: Year 2 | F3: Year 3 | G3: Year 4 | H3: Year 5 | I3: Year 6 | J3: Year 7 | K3: Year 8 | L3: Year 9 | M3: Year 10
C4: 2014 | D4: 2015 | E4: 2016 | F4: 2017 | G4: 2018 | H4: 2019 | I4: 2020 | J4: 2021 | K4: 2022 | L4: 2023 | M4: 2024
B5: Dividend Growth rate | D5: 0.03 | E5: 0.03 | F5: 0.03 | G5: 0.05 | H5: 0.05 | I5: 0.05 | J5: 0.05 | K5: 0.05 | L5: 0.05
B6: Dividend Per Share | C6: 0.86 | D6: 0.89 | E6: 0.91 | F6: 0.94 | G6: 0.99 | H6: 1.04 | I6: 1.09 | J6: 1.14 | K6: 1.2 | L6: 1.26
B7: Terminal value | L7: =L6*(1+7%)/(10.43%-7%) -> 39.306122
B8: Dividend + Terminal Value | D8: =D6+D7 -> 0.89 | E8: =E6+E7 -> 0.91 | F8: =F6+F7 -> 0.94 | G8: =G6+G7 -> 0.99 | H8: =H6+H7 -> 1.04 | I8: =I6+I7 -> 1.09 | J8: =J6+J7 -> 1.14 | K8: =K6+K7 -> 1.2 | L8: =L6+L7 -> 40.566122
B10: Discounted Dividend value Per Share | C10: =NPV(Valuation!H4,DDM!D8:L8) -> 21.871676

Sheet Comparables
C3: SCB | D3: RBS | E3: Barclays | F3: HSBC | G3: UBS | H3: ING | I3: Deutsche Bank | J3: Average | K3: Price Per Share (SCB Multiples) | L3: Price Per Share (Comparables)
B4: P/E | C4: 9.23 | D4: 0.12 | E4: 0.1 | F4: 6.69 | G4: 11.16 | H4: 10.02 | I4: 21.77 | J4: =AVERAGE(D4:I4) -> 8.31 | K4: =C4*FCFE!D16 -> 19.85694 | L4: =J4*FCFE!D16 -> 17.8777
B5: P/S | C5: 2.23 | D5: 3.08 | E5: 2.21 | F5: 2.07 | G5: 2.11 | H5: 3.39 | I5: 1.24 | J5: =AVERAGE(D5:I5) -> 2.35 | K5: =C5*FCFE!D5/Valuation!C9 -> 16.976698 | L5: =J5*FCFE!D5/Valuation!C9 -> 17.890242
B6: P/B | C6: 0.74 | D6: 0.71 | E6: 0.89 | F6: 0.62 | G6: 1.17 | H6: 0.92 | I6: 0.55 | J6: =AVERAGE(D6:I6) -> 0.81 | K6: =C6*Valuation!C14 -> 14.097 | L6: =J6*Valuation!C14 -> 15.4305
K7: =AVERAGE(K4:K6) -> 16.976879 | L7: =AVERAGE(L4:L6) -> 17.066147
